pebble/__init__.py
pebble/interpreter.py
pebble_lang-2.2.0.dist-info/licenses/LICENSE
pebble_lang-2.2.0.dist-info/METADATA
pebble_lang-2.2.0.dist-info/WHEEL
pebble_lang-2.2.0.dist-info/entry_points.txt
pebble_lang-2.2.0.dist-info/top_level.txt
pebble_lang-2.2.0.dist-info/RECORD
